Vreau_sa_dorm/__init__.py
Vreau_sa_dorm/andreea.py
Vreau_sa_dorm-0.1.3.dist-info/METADATA
Vreau_sa_dorm-0.1.3.dist-info/WHEEL
Vreau_sa_dorm-0.1.3.dist-info/top_level.txt
Vreau_sa_dorm-0.1.3.dist-info/RECORD
