Metadata-Version: 2.1
Name: Vreau-sa-dorm
Version: 0.1.3
Summary: First project
Home-page: UNKNOWN
Author: Andreea Teku
Author-email: andreea.teku@gmail.com
License: UNKNOWN
Platform: UNKNOWN
